csvtrans/__init__.py
csvtrans/__main__.py
csvtrans/utils.py
csvtrans_cupack-0.1.0.dist-info/METADATA
csvtrans_cupack-0.1.0.dist-info/WHEEL
csvtrans_cupack-0.1.0.dist-info/top_level.txt
csvtrans_cupack-0.1.0.dist-info/RECORD
