Metadata-Version: 2.1
Name: csvtrans_cupack
Version: 0.1.0
Summary: Конвертация данных из csv и суммирование доходов и расходов
Author: elhuel
License: CU
Requires-Python: >=3.10
